librarypaste/__init__.py
librarypaste/__main__.py
librarypaste/datastore.py
librarypaste/jsonstore.py
librarypaste/launch.py
librarypaste/mongostore.py
librarypaste/pastebin.py
librarypaste/pmxbot.py
librarypaste/template.py
librarypaste/static/base.css
librarypaste/static/favicon.ico
librarypaste/static/librarypaste.png
librarypaste/static/pygments.css
librarypaste/templates/about.html
librarypaste/templates/base.html
librarypaste/templates/entry.html
librarypaste/templates/file.html
librarypaste/templates/view.html
librarypaste-3.10.0.dist-info/LICENSE
librarypaste-3.10.0.dist-info/METADATA
librarypaste-3.10.0.dist-info/WHEEL
librarypaste-3.10.0.dist-info/entry_points.txt
librarypaste-3.10.0.dist-info/top_level.txt
librarypaste-3.10.0.dist-info/RECORD
