Metadata-Version: 2.1
Name: librarypaste
Version: 3.10.0
Summary: A simple pastebin implemented in Python
Home-page: https://github.com/jaraco/librarypaste
Author: Jason R. Coombs
Author-email: jaraco@jaraco.com
Classifier: Development Status :: 5 - Production/Stable
Classifier: Intended Audience :: Developers
Classifier: License :: OSI Approved :: MIT License
Classifier: Programming Language :: Python :: 3
Classifier: Programming Language :: Python :: 3 :: Only
Requires-Python: >=3.8
License-File: LICENSE
Requires-Dist: pygments
Requires-Dist: genshi
Requires-Dist: cherrypy
Requires-Dist: PyYAML
Requires-Dist: requests
Requires-Dist: jaraco.functools >=1.15
Requires-Dist: more-itertools
Requires-Dist: importlib-metadata
Requires-Dist: importlib-resources
Requires-Dist: puremagic
Requires-Dist: jaraco.context
Provides-Extra: docs
Requires-Dist: sphinx >=3.5 ; extra == 'docs'
Requires-Dist: jaraco.packaging >=9.3 ; extra == 'docs'
Requires-Dist: rst.linker >=1.9 ; extra == 'docs'
Requires-Dist: furo ; extra == 'docs'
Requires-Dist: sphinx-lint ; extra == 'docs'
Provides-Extra: testing
Requires-Dist: pytest >=6 ; extra == 'testing'
Requires-Dist: pytest-checkdocs >=2.4 ; extra == 'testing'
Requires-Dist: pytest-cov ; extra == 'testing'
Requires-Dist: pytest-mypy ; extra == 'testing'
Requires-Dist: pytest-enabler >=2.2 ; extra == 'testing'
Requires-Dist: pytest-ruff >=0.2.1 ; extra == 'testing'
Requires-Dist: pymongo >=3 ; extra == 'testing'
Requires-Dist: jaraco.mongodb >=11.5.1 ; extra == 'testing'
Requires-Dist: types-pyyaml ; extra == 'testing'
